wutu/__init__.py
wutu/app.py
wutu/compiler.py
wutu/decorators.py
wutu/module.py
wutu/test_util.py
wutu/util.py
wutu/version.py
wutu/compiler/__init__.py
wutu/compiler/common.py
wutu/compiler/compiler.py
wutu/compiler/controller.py
wutu/compiler/grammar.py
wutu/compiler/http.py
wutu/compiler/service.py
wutu/compiler/snippet.py
wutu/tests/__init__.py
wutu/tests/util_tests.py
wutu-0.1.5.dist-info/DESCRIPTION.rst
wutu-0.1.5.dist-info/METADATA
wutu-0.1.5.dist-info/RECORD
wutu-0.1.5.dist-info/WHEEL
wutu-0.1.5.dist-info/metadata.json
wutu-0.1.5.dist-info/top_level.txt
