Metadata-Version: 2.0
Name: wutu
Version: 0.1.5
Summary: A minimalistic python-angular framework
Home-page: https://github.com/zaibacu/wutu
Author: Šarūnas Navickas
Author-email: zaibacu@gmail.com
License: MIT
Platform: UNKNOWN
Requires-Dist: flask (==0.10.1)
Requires-Dist: flask-restful (==0.2.12)
Requires-Dist: jsbeautifier (==1.5.10)
Requires-Dist: jsmin (==2.1.4)
Requires-Dist: logbook (==0.10.1)
Requires-Dist: mypy-lang (==0.2.0)
Requires-Dist: naked (==0.1.31)
